hwc_ndarray_letterbox.py
hwc_ndarray_letterbox-0.1.0a0.dist-info/licenses/LICENSE
hwc_ndarray_letterbox-0.1.0a0.dist-info/METADATA
hwc_ndarray_letterbox-0.1.0a0.dist-info/WHEEL
hwc_ndarray_letterbox-0.1.0a0.dist-info/top_level.txt
hwc_ndarray_letterbox-0.1.0a0.dist-info/RECORD
