Metadata-Version: 2.4
Name: hwc-ndarray-letterbox
Version: 0.1.0a0
Summary: Letterbox an HWC ndarray image to fit the target width and height while updating the homogeneous transformation matrix.
Author-email: Jifeng Wu <jifengwu2k@gmail.com>
License-Expression: MIT
Project-URL: Homepage, https://github.com/jifengwu2k/hwc-ndarray-letterbox
Project-URL: Bug Tracker, https://github.com/jifengwu2k/hwc-ndarray-letterbox/issues
Classifier: Programming Language :: Python :: 2
Classifier: Programming Language :: Python :: 3
Classifier: Operating System :: OS Independent
Requires-Python: >=2
License-File: LICENSE
Requires-Dist: numpy
Requires-Dist: opencv-python-headless
Requires-Dist: typing; python_version < "3.5"
Dynamic: license-file
